{
    "courses": [
        {
            "institution": "TOWSN",
            "acadCareer": "UGRD",
            "subject": "MATH",
            "catalogNumber": "95",
            "courseTitle": "DEVELOPMENTAL MATHEMATICS",
            "termsOffered": "Fall & Spring",
            "description": "A review of elementary and intermediate algebra including equations and inequalities, graphing linear equations, exponents and polynomials.",
            "units": "4",
            "gradingBasis": "S/U",
            "prerequisites": []
        },
        {
            "institution": "TOWSN",
            "acadCareer": "UGRD",
            "subject": "MATH",
            "catalogNumber": "100",
            "courseTitle": "FOUNDATIONS OF MATHEMATICAL REASONING",
            "termsOffered": "Fall, Spring & Summer",
            "description": "Designed to provide students the necessary mathematical knowledge and skills associated with quantitative literacy needed for success in various Core courses.",
            "units": "3",
            "gradingBasis": "UNDERGRADUATE GRADING",
            "prerequisites": []
        },
        {
            "institution": "TOWSN",
            "acadCareer": "UGRD",
            "subject": "MATH",
            "catalogNumber": "102",
            "courseTitle": "INTERMEDIATE ALGEBRA",
            "termsOffered": "Fall, Spring & Summer",
            "description": "Topics include: factoring of polynomials, rational expressions and equations, graphs, relations and functions, radicals and exponents, and quadratic equations.",
            "units": "3",
            "gradingBasis": "UNDERGRADUATE GRADING",
            "prerequisites": ["MATH 95 or DVMT 101"]
        },
        {
            "institution": "TOWSN",
            "acadCareer": "UGRD",
            "subject": "MATH",
            "catalogNumber": "105",
            "courseTitle": "MATHEMATICAL IDEAS",
            "termsOffered": "Fall & Spring",
            "description": "Basic concepts and ideas in mathematics exploring the aesthetics and utility of mathematics.",
            "units": "3",
            "gradingBasis": "UNDERGRADUATE GRADING",
            "prerequisites": ["MATH 100"]
        },
        {
            "institution": "TOWSN",
            "acadCareer": "UGRD",
            "subject": "MATH",
            "catalogNumber": "109",
            "courseTitle": "TRANSITION TO ALGEBRA FOR APPLICATIONS",
            "termsOffered": "Fall & Spring",
            "description": "A two-part course with DVMT 110 and MATH 111. Designed for students in the developmental math program.",
            "units": "3",
            "gradingBasis": "UNDERGRADUATE GRADING",
            "prerequisites": ["DVMT 101"]
        },
        {
            "institution": "TOWSN",
            "acadCareer": "UGRD",
            "subject": "MATH",
            "catalogNumber": "111",
            "courseTitle": "FINITE MATHEMATICS",
            "termsOffered": "Fall & Spring",
            "description": "Applications of finite mathematics: linear equations, matrices, linear programming, sets and counting, probability, and difference equations.",
            "units": "3",
            "gradingBasis": "UNDERGRADUATE GRADING",
            "prerequisites": ["MATH 100"]
        },
        {
            "institution": "TOWSN",
            "acadCareer": "UGRD",
            "subject": "MATH",
            "catalogNumber": "115",
            "courseTitle": "COLLEGE ALGEBRA",
            "termsOffered": "Fall, Spring & Summer",
            "description": "Equations and the concept of functions; linear, quadratic, polynomial, exponential, logarithmic, and rational functions.",
            "units": "3",
            "gradingBasis": "UNDERGRADUATE GRADING",
            "prerequisites": ["MATH 102"]
        },
        {
            "institution": "TOWSN",
            "acadCareer": "UGRD",
            "subject": "MATH",
            "catalogNumber": "117",
            "courseTitle": "TRIGONOMETRY AND ADVANCED COLLEGE ALGEBRA",
            "termsOffered": "Fall & Spring",
            "description": "The second semester in a two-semester precalculus sequence, focusing on trigonometry.",
            "units": "3",
            "gradingBasis": "UNDERGRADUATE GRADING",
            "prerequisites": ["MATH 115"]
        },
        {
            "institution": "TOWSN",
            "acadCareer": "UGRD",
            "subject": "MATH",
            "catalogNumber": "119",
            "courseTitle": "PRE-CALCULUS",
            "termsOffered": "Fall, Spring & Summer",
            "description": "An overview of functions and their graphs as well as algebraic techniques and trigonometry in preparation for Calculus I.",
            "units": "4",
            "gradingBasis": "UNDERGRADUATE GRADING",
            "prerequisites": []
        },
        {
            "institution": "TOWSN",
            "acadCareer": "UGRD",
            "subject": "MATH",
            "catalogNumber": "119S",
            "courseTitle": "CONNECTIONS TO PRE-CALCULUS",
            "termsOffered": "Fall & Spring",
            "description": "Explorations to support MATH 119. Helps students to review prior mathematical knowledge.",
            "units": "1",
            "gradingBasis": "S/U",
            "prerequisites": [],
            "corequisites": ["MATH 119"]
        },
        {
            "institution": "TOWSN",
            "acadCareer": "UGRD",
            "subject": "MATH",
            "catalogNumber": "204",
            "courseTitle": "MATHEMATICAL CONCEPTS AND STRUCTURES I",
            "termsOffered": "Fall, Spring & Summer",
            "description": "Content knowledge for teaching elementary school mathematics. Problem solving, systems of numeration, and arithmetic properties.",
            "units": "4",
            "gradingBasis": "UNDERGRADUATE GRADING",
            "prerequisites": ["MATH 100"]
        },
        {
            "institution": "TOWSN",
            "acadCareer": "UGRD",
            "subject": "MATH",
            "catalogNumber": "205",
            "courseTitle": "MATHEMATICAL CONCEPTS AND STRUCTURES II",
            "termsOffered": "Fall & Spring",
            "description": "Proportional reasoning, algebra, statistics, and probability concepts through statistical investigations.",
            "units": "4",
            "gradingBasis": "UNDERGRADUATE GRADING",
            "prerequisites": ["MATH 204"]
        },
        {
            "institution": "TOWSN",
            "acadCareer": "UGRD",
            "subject": "MATH",
            "catalogNumber": "211",
            "courseTitle": "CALCULUS FOR APPLICATIONS",
            "termsOffered": "Fall, Spring & Summer",
            "description": "Elements of differential and integral calculus with applications to biology, business, economics, psychology, and social sciences.",
            "units": "3",
            "gradingBasis": "UNDERGRADUATE GRADING",
            "prerequisites": ["MATH 115 or MATH 119"]
        },
        {
            "institution": "TOWSN",
            "acadCareer": "UGRD",
            "subject": "MATH",
            "catalogNumber": "215",
            "courseTitle": "RATIONAL NUMBERS AND PROPORTIONAL REASONING FOR MIDDLE SCHOOL TEACHERS",
            "termsOffered": "Fall & Spring",
            "description": "Thorough and rigorous treatment of concepts in rational numbers, ratios, and proportional reasoning for middle school math.",
            "units": "4",
            "gradingBasis": "UNDERGRADUATE GRADING",
            "prerequisites": ["MATH 119 or MATH 273"]
        },
        {
            "institution": "TOWSN",
            "acadCareer": "UGRD",
            "subject": "MATH",
            "catalogNumber": "223",
            "courseTitle": "PEDAGOGICAL CONTENT KNOWLEDGE FOR MIDDLE SCHOOL MATHEMATICS",
            "termsOffered": "Fall",
            "description": "Focus on teaching middle school mathematics, including proportional reasoning, expressions, equations, and functions.",
            "units": "2",
            "gradingBasis": "UNDERGRADUATE GRADING",
            "prerequisites": ["SEMS 130 or SEMS 110 and SEMS 120"]
        },
        {
            "institution": "TOWSN",
            "acadCareer": "UGRD",
            "subject": "MATH",
            "catalogNumber": "225",
            "courseTitle": "ALGEBRA AND NUMBER CONCEPTS FOR MIDDLE SCHOOL TEACHERS",
            "termsOffered": "Spring",
            "description": "In-depth treatment of number theory and algebra topics for middle school teachers, including factors, sequences, and functions.",
            "units": "4",
            "gradingBasis": "UNDERGRADUATE GRADING",
            "prerequisites": ["MATH 273"]
        },
        {
            "institution": "TOWSN",
            "acadCareer": "UGRD",
            "subject": "MATH",
            "catalogNumber": "231",
            "courseTitle": "BASIC STATISTICS",
            "termsOffered": "Fall, Spring & Summer",
            "description": "Introduction to statistics with applications in various fields. Emphasis on data collection, confidence intervals, hypothesis testing, and regression.",
            "units": "3",
            "gradingBasis": "UNDERGRADUATE GRADING",
            "prerequisites": ["MATH 100 or MATH 102"]
        },
        {
            "institution": "TOWSN",
            "acadCareer": "UGRD",
            "subject": "MATH",
            "catalogNumber": "237",
            "courseTitle": "ELEMENTARY BIOSTATISTICS",
            "termsOffered": "Fall & Spring",
            "description": "Elementary statistical concepts with application to biological and health sciences.",
            "units": "4",
            "gradingBasis": "UNDERGRADUATE GRADING",
            "prerequisites": ["MATH 100 or MATH 102"]
        },
        {
            "institution": "TOWSN",
            "acadCareer": "UGRD",
            "subject": "MATH",
            "catalogNumber": "265",
            "courseTitle": "ELEMENTARY LINEAR ALGEBRA",
            "termsOffered": "Fall & Spring",
            "description": "Topics include matrix calculations, vector spaces, linear transformations, and eigenvalues.",
            "units": "4",
            "gradingBasis": "UNDERGRADUATE GRADING",
            "prerequisites": ["MATH 211 or MATH 273"]
        },
        {
            "institution": "TOWSN",
            "acadCareer": "UGRD",
            "subject": "MATH",
            "catalogNumber": "273",
            "courseTitle": "CALCULUS I",
            "termsOffered": "Fall, Spring & Summer",
            "description": "Functions, limits, continuity, differentiation, introduction to integration, and applications.",
            "units": "4",
            "gradingBasis": "UNDERGRADUATE GRADING",
            "prerequisites": ["MATH 117 or MATH 119"]
        },
        {
            "institution": "TOWSN",
            "acadCareer": "UGRD",
            "subject": "MATH",
            "catalogNumber": "274",
            "courseTitle": "CALCULUS II",
            "termsOffered": "Fall & Spring",
            "description": "Differentiation and integration of exponential, logarithmic, and inverse trigonometric functions, techniques of integration, sequences, and series.",
            "units": "4",
            "gradingBasis": "UNDERGRADUATE GRADING",
            "prerequisites": ["MATH 273"]
        },
        {
            "institution": "TOWSN",
            "acadCareer": "UGRD",
            "subject": "MATH",
            "catalogNumber": "275",
            "courseTitle": "CALCULUS III",
            "termsOffered": "Fall & Spring",
            "description": "Vectors, differential and integral calculus of functions of several variables.",
            "units": "4",
            "gradingBasis": "UNDERGRADUATE GRADING",
            "prerequisites": ["MATH 274"]
        },
        {
            "institution": "TOWSN",
            "acadCareer": "UGRD",
            "subject": "MATH",
            "catalogNumber": "310",
            "courseTitle": "FUNCTIONS AND MODELING FOR SECONDARY SCHOOL TEACHERS",
            "termsOffered": "Fall & Spring",
            "description": "Broadens content knowledge for teaching secondary mathematics, focusing on modeling and functions.",
            "units": "3",
            "gradingBasis": "UNDERGRADUATE GRADING",
            "prerequisites": ["MATH 273", "MATH 274", "MATH 265"]
        },
        {
            "institution": "TOWSN",
            "acadCareer": "UGRD",
            "subject": "MATH",
            "catalogNumber": "312",
            "courseTitle": "THEORY OF INTEREST",
            "termsOffered": "Spring",
            "description": "Covers financial management concepts such as annuities, amortization, and bonds.",
            "units": "4",
            "gradingBasis": "UNDERGRADUATE GRADING",
            "prerequisites": ["MATH 274"]
        },
        {
            "institution": "TOWSN",
            "acadCareer": "UGRD",
            "subject": "MATH",
            "catalogNumber": "314",
            "courseTitle": "INTRODUCTION TO CRYPTOGRAPHY",
            "termsOffered": "Fall",
            "description": "Covers the mathematical foundations of cryptography, including number theory and modern cryptosystems.",
            "units": "3",
            "gradingBasis": "UNDERGRADUATE GRADING",
            "prerequisites": ["COSC 236", "MATH 263", "MATH 330"]
        },
        {
            "institution": "TOWSN",
            "acadCareer": "UGRD",
            "subject": "MATH",
            "catalogNumber": "315",
            "courseTitle": "APPLIED COMBINATORICS",
            "termsOffered": "Spring",
            "description": "Topics include counting methods, recurrence relations, permutations, and graph theory applications.",
            "units": "4",
            "gradingBasis": "UNDERGRADUATE GRADING",
            "prerequisites": ["MATH 274", "MATH 263"]
        },
        {
            "institution": "TOWSN",
            "acadCareer": "UGRD",
            "subject": "MATH",
            "catalogNumber": "374",
            "courseTitle": "DIFFERENTIAL EQUATIONS",
            "termsOffered": "Fall & Spring",
            "description": "Covers linear and nonlinear differential equations, including techniques for solving them.",
            "units": "3",
            "gradingBasis": "UNDERGRADUATE GRADING",
            "prerequisites": ["MATH 274"]
        },
        {
            "institution": "TOWSN",
            "acadCareer": "UGRD",
            "subject": "MATH",
            "catalogNumber": "377",
            "courseTitle": "MATHEMATICAL MODELS",
            "termsOffered": "Fall",
            "description": "Developing mathematical models for applications in sociology, economics, and ecology.",
            "units": "3",
            "gradingBasis": "UNDERGRADUATE GRADING",
            "prerequisites": ["MATH 265", "MATH 274", "COSC 236"]
        },
        {
            "institution": "TOWSN",
            "acadCareer": "UGRD",
            "subject": "MATH",
            "catalogNumber": "465",
            "courseTitle": "NUMBER THEORY",
            "termsOffered": "Spring",
            "description": "Introduction to prime numbers, modular arithmetic, and applications in cryptography.",
            "units": "3",
            "gradingBasis": "UNDERGRADUATE GRADING",
            "prerequisites": ["MATH 263", "MATH 274"]
        },
        {
            "institution": "TOWSN",
            "acadCareer": "UGRD",
            "subject": "MATH",
            "catalogNumber": "475",
            "courseTitle": "COMPLEX ANALYSIS",
            "termsOffered": "Spring",
            "description": "Explores complex number systems, Cauchy’s integral theorem, and residue theorem applications.",
            "units": "3",
            "gradingBasis": "UNDERGRADUATE GRADING",
            "prerequisites": ["MATH 267", "MATH 275"]
        },
        {
            "institution": "TOWSN",
            "acadCareer": "UGRD",
            "subject": "MATH",
            "catalogNumber": "485",
            "courseTitle": "MATHEMATICAL FINANCE",
            "termsOffered": "Fall",
            "description": "Covers financial derivatives, option pricing, and risk management techniques.",
            "units": "3",
            "gradingBasis": "UNDERGRADUATE GRADING",
            "prerequisites": ["MATH 331"]
        },
        {
            "institution": "TOWSN",
            "acadCareer": "UGRD",
            "subject": "MATH",
            "catalogNumber": "491",
            "courseTitle": "READINGS IN MATHEMATICS",
            "termsOffered": "Fall, Spring & Summer",
            "description": "Independent reading in selected areas of mathematics, tailored to student needs.",
            "units": "1-3",
            "gradingBasis": "UNDERGRADUATE GRADING",
            "prerequisites": ["Senior Standing", "Consent of Instructor"]
        },
        {
            "institution": "TOWSN",
            "acadCareer": "UGRD",
            "subject": "MATH",
            "catalogNumber": "499",
            "courseTitle": "HONORS THESIS IN MATHEMATICS",
            "termsOffered": "Fall & Spring",
            "description": "Writing an honors thesis based on supervised independent research in mathematics.",
            "units": "1",
            "gradingBasis": "UNDERGRADUATE GRADING",
            "prerequisites": ["Senior Standing", "Consent of Department"]
        }
    ]
}
